conda_forge_metadata/__init__.py
conda_forge_metadata/_version.py
conda_forge_metadata/feedstock_outputs.py
conda_forge_metadata/libcfgraph.py
conda_forge_metadata/oci.py
conda_forge_metadata/py.typed
conda_forge_metadata/repodata.py
conda_forge_metadata/streaming.py
conda_forge_metadata/types.py
conda_forge_metadata/artifact_info/__init__.py
conda_forge_metadata/artifact_info/info_json.py
conda_forge_metadata/autotick_bot/__init__.py
conda_forge_metadata/autotick_bot/import_to_pkg.py
conda_forge_metadata/autotick_bot/pypi_to_conda.py
conda_forge_metadata-0.12.0.dist-info/licenses/LICENSE
conda_forge_metadata-0.12.0.dist-info/METADATA
conda_forge_metadata-0.12.0.dist-info/WHEEL
conda_forge_metadata-0.12.0.dist-info/top_level.txt
conda_forge_metadata-0.12.0.dist-info/RECORD
