Metadata-Version: 2.4
Name: conda-forge-metadata
Version: 0.12.0
Summary: programatic access to conda-forge's metadata
Author-email: conda-forge-tick development team <condaforge@gmail.com>
License: BSD 3-Clause License
Project-URL: home, https://github.com/conda-forge/conda-forge-metadata
License-File: LICENSE
Requires-Dist: deprecated
Requires-Dist: requests
Requires-Dist: ruamel.yaml
Requires-Dist: typing-extensions
Requires-Dist: beautifulsoup4
Requires-Dist: conda-oci-mirror
Requires-Dist: conda_package_streaming>=0.12.0
Provides-Extra: oci
Requires-Dist: conda-oci-mirror; extra == "oci"
Dynamic: license-file
